<?xml version="1.0" standalone="yes"?>
<Root><Schema xmlns="urn:schemas-microsoft-com:xml-data" name="SVR00001" xmlns:dt="urn:schemas-microsoft-com:datatypes"><AttributeType name="Name" dt:type="string"/><AttributeType name="Value" dt:type="string"/><AttributeType name="Type" dt:type="string"/><ElementType name="DATA" content="mixed" model="closed"><attribute type="Name" required="yes"/><attribute type="Type" required="yes"/></ElementType><ElementType name="NODE" content="mixed" model="closed"><attribute type="Name" required="yes"/><attribute type="Type" required="no"/><element type="NODE" minOccurs="0" maxOccurs="*"/><element type="DATA" minOccurs="0" maxOccurs="1"/></ElementType><AttributeType name="Format" dt:type="string"/><AttributeType name="FormatVersion" dt:type="string"/><AttributeType name="Revision" dt:type="string"/><ElementType name="Revision" content="mixed" model="closed"><attribute type="Format" required="yes"/><attribute type="FormatVersion" required="yes"/><attribute type="Revision" required="yes"/><element type="DATA" minOccurs="0" maxOccurs="1"/></ElementType><ElementType name="RevisionHistory" content="mixed" model="closed"><element type="Revision" minOccurs="1" maxOccurs="*"/><element type="DATA" minOccurs="0" maxOccurs="1"/></ElementType><AttributeType name="IsActive" dt:type="string"/><ElementType name="Encryption" content="mixed" model="closed"><attribute type="IsActive" required="yes"/><element type="DATA" minOccurs="0" maxOccurs="1"/></ElementType></Schema><Encryption xmlns="x-schema:#SVR00001" IsActive="TRUE"><DATA Name="o@FPgHGbGuJlRJaf4sBeRHWcylIrf" Type="Td8DoHafwOxz@Iqg8vssf">Mg80DJGb8p856LWlXmJnvGqkgZ68cSa4EsR@uIGc3iyha5a5yIqJr</DATA></Encryption><NODE xmlns="x-schema:#SVR00001" Name="sLmutvbä" Type="XwbcNcHaJ29bqaHazaRäPbHaybaal">
<DATA Name="x2ltUgT9XltE" Type="RU8okIqfRiPRI@GLB03EpHqArnwrNHGcXc4bl">BsLaxIafrJULäYabWQHAnJqgu70th</DATA>
<DATA Name="T6O6yPIdEUZAWäC72rAy" Type="SY7sdGGbgCConJWc9m5Vf">oQEjLGqgXSD3p</DATA>
<DATA Name="wlBIpNd5räeA5dds" Type="DVXnkIWdgaXYKVGfOpYxhLOvaLFkb9WovOMtNHGaVHTIp"></DATA>
<DATA Name="Cemo9Nd5räeA5dds" Type="TccokIGbL61tNHWczwxIs"></DATA>
<DATA Name="T6O6v28uP2l5V7L9XltE" Type="BUSskIqhocgn2VGLmLxCJ7abpwr0XMq5bnfvNHGabiINs">ltqZwIGbGRmnnJqgmFGoo</DATA>
<NODE Name="qqbBXBquD7s7">
</NODE>
<NODE Name="sLmg9bAc">
</NODE>
<NODE Name="qqbBXBquD7s7">
<NODE Name="KoXL">
<DATA Name="j8e39eIZWäeW5bA7" Type="BcYokIGbbHkrNHWce1Ldm">BtqWwIGbWRmknJqg1xIlg</DATA>
<DATA Name="W67FUahMcJ0L" Type="TY8EkIafLRYKNHWctoB6p">FkXfEHWbTJR@uIGbJybkjJWUmzXyQJGc8Aybe</DATA>
<DATA Name="hILK" Type="TZ8rdGGbhDDnnJWc8N4Ur">BVIDMMan7xTdCJafVNKpCHWkuW11j</DATA>
</NODE>
<NODE Name="WSMTnaR@tkxTv6vP9l2F8y@uD9XH">
<DATA Name="j8e39eIZWäeW5bA7" Type="RZaEkIGbrszGNHqg4TwAm">mcH@wIGdbGX4A83UHADonJqeHgZpl</DATA>
<DATA Name="W67FUahMcJ0L" Type="TZ7DkIGbLSXJNHqg@nAAe">Bo1uEHGbiD1NQJqfh29beLGn5OXvH0yIPNWdvIGcXCä3p</DATA>
<DATA Name="hILK" Type="DVbFdGGdJlplY7392yHAnJqeVJxtf">shI6sJafHhEWBJGbCtH@TGWcRcVdj</DATA>
</NODE>
<NODE Name="WNj8HHm9upä3rokFx2käWäfb9oVs">
<DATA Name="j8e39eIZWäeW5bA7" Type="R9SEkIafrDfHNHqg@yQre">m9uäwIafHwrznJWcpOhqo</DATA>
<DATA Name="W67FUahMcJ0L" Type="Ah4Pt@WLAD96IPG0124rxQ31DUXokIafvNMuNHaelGhPs">B9LjEHGbinMCQJGbPxG3uIWc4Mhhs</DATA>
<DATA Name="hILK" Type="Cc9rdGWbVhdOy1aPJuLuw93U1RDnnJGcew6ed">MmIptJGb0mEeCJafW@IiUGWcuhV2d</DATA>
</NODE>
<NODE Name="JgC0UcnOVJXEyGd2bqbcOBquufbH">
<DATA Name="j8e39eIZWäeW5bA7" Type="B9bEkIGbSCtq2RWN5bakySOvJ8LXG5G0R7kbVLqkd5@apJamMWFWe">mduaxIGbd2G@AMWkPNe4k</DATA>
<DATA Name="W67FUahMcJ0L" Type="DäXHkIWbnf10K7Ofl5GvbWq5v3MNNHGch6fwj">El1zEHGblA1SQJafSKWivIWc14Dxp</DATA>
<DATA Name="hILK" Type="6EBBgGGj2ynjnJWcfjJGd">UlDltJahjxqNIYil8lzaCJGd0gPTuZ3EX22iCHGi2oiXm</DATA>
</NODE>
<NODE Name="UcnOVJXEyGd2bqbcOBquufbH">
<DATA Name="j8e39eIZWäeW5bA7" Type="BVaIkIGbbozKNHWcKRuws">msHäwIGbHQDznJWcHE6sr</DATA>
<DATA Name="W67FUahMcJ0L" Type="DV8okIafvOYuNHqgbH6dd">AoMfEHahH3DvSRyYPoKrGOODhDMyQJGbONG@uIaes9NHj</DATA>
<DATA Name="hILK" Type="S98ndGafmq6sAMqoCAtkm">ElXptJGbTlTeCJafORSiUGqgQoEDm</DATA>
</NODE>
<NODE Name="sR8V2529">
<DATA Name="j8e39eIZWäeW5bA7" Type="RVTnkIqfeVMcQ2i4cSZ6mGyArogqNHGcäjHOo">CtvaxIGbXRrAnJqgZ8LBl</DATA>
<DATA Name="W67FUahMcJ0L" Type="TUXokIGbLNMuNHqg8Qpbm">käHuEHaf2nINQJahktyvISWwyyCdvIqecVJWo</DATA>
<DATA Name="hILK" Type="S9TsdGafgOnonJWcssdTe">uiHäsJGbhr5O2MGjEmw3TGWcdlSVs</DATA>
</NODE>
<NODE Name="CnhJnlw3W68V2529">
<DATA Name="j8e39eIZWäeW5bA7" Type="RYWDkIafrrjGNHqgCgg5r">B9KaxIGdX@gfCH3EWwHAnJqe5GDzq</DATA>
<DATA Name="W67FUahMcJ0L" Type="oRTZVXytäPjtb3OVL6YxNHWaOXBAo93ETc9rkIGcDu6Kq">poHeEHGb7CHxQJGbDNBZuIWcL9iIj</DATA>
<DATA Name="hILK" Type="DUXodGaf2xrknJWcLcLlj">px77LMqnXdH2TGGb79R0PäqY1lAZBJGc7gJKr</DATA>
</NODE>
<NODE Name="CeodK5alqBquufbH">
<DATA Name="j8e39eIZWäeW5bA7" Type="BUXDkIafbnkGNHqgLQpyn">lätVwIGbGxqjnJWcabUQi</DATA>
<DATA Name="W67FUahMcJ0L" Type="Dd9IkIqhLcC7YHiXq@Vw2PGLtKytfUWwv7YONHaej84Dq">päKvEHGb3BkrvNGjDyFevIWchNM4k</DATA>
<DATA Name="hILK" Type="T97IdGGbhOCEnJWcr35vd">yCT9sJWdeON2TGGbiIKQiäirT1CäpJq5NCPZBJGahv3Sh</DATA>
</NODE>
<NODE Name="JmMTnaR@tkxTv6vP9l2F8FCui9Yc">
<DATA Name="j8e39eIZWäeW5bA7" Type="RZbJkIGbrsALNHWczLvDh">BdL@wIGbWBHonJWcyNäNj</DATA>
<DATA Name="W67FUahMcJ0L" Type="DUTDkIGbvNIJNHWckIHWq">AlLjEHWbtmbDP4WxEtlnlK37hALCQJWb8yz7UUiQVJxz9ZyYOKF3uIGcyXMhn</DATA>
<DATA Name="hILK" Type="TZ7IdGGbhDCEnJWcBVqvp">OxI6sJaf2xEWBJWb@SAajWiPqZehcTqAupy@TGGct5fld</DATA>
</NODE>
<NODE Name="sLmg23Ju">
<DATA Name="j8e39eIZWäeW5bA7" Type="BdbIkIGbbIzKNHWceä@9r">CsqexIGb4AsGuQijXQmEnJWc41iDd</DATA>
<DATA Name="W67FUahMcJ0L" Type="DUSHkIGbvNHNNHWclII9j">kl1eEHGb2z1xQJGbBqJMURibyKWZuIWca4FGq</DATA>
<DATA Name="hILK" Type="4g5LgGGj1SConJWcIx3nq">WlHäsJGbälD@BJGbCRI3TGqgDKMhd</DATA>
</NODE>
<NODE Name="PälpM0ezROlcQSMc36B729XY8ySu5jFE">
<DATA Name="j8e39eIZWäeW5bA7" Type="R97nkIafrDvqNHWcZYAio">loGäwIGdpE7n833oGMCznJWagyWsm</DATA>
<DATA Name="W67FUahMcJ0L" Type="ZMMIWNO0VYEfuOibTZ7skIWbrw9FnQaP9idTääW9LSXyNHGcYT3Vj">kpYfEHaf2DYyQJGbyOS@uIWcOx6be</DATA>
<DATA Name="hILK" Type="TUSEdGafhymAnJWczQOzo">SlEäsJWdIkA0EOq5BY4mAGizHfjl0Yi56lA@BJGdApnZX1OmKcH3TGqe3KHNs</DATA>
</NODE>
</NODE>
<NODE Name="qqbBXBqg20hu">
<NODE Name="Tä8Lsv629NbM8taGtEYc">
<DATA Name="j8e39eIZWäeW5bA7" Type="BVXnkIWbgxzIS1GDvyzy7YWMbokqNHGcpjfcs">C9JWwIafXwGknJqgFOwPk</DATA>
<DATA Name="W67FUahMcJ0L" Type="DYaokIWbegOJv2qYgDKGN@qavR0tNHqeQMEkq">A9WyEHafhnXRQJGbqVwpQKqo3mYuh</DATA>
<DATA Name="hILK" Type="TäTsdGGbhPnonJWc0tlLd">uPq@QTOFqXlwp4WvLhXotJWbb5WKFLO1vwämWMqk@hTdCJaf1@VhUGae@G@9s</DATA>
</NODE>
</NODE>
<NODE Name="qqbBXBqrXmq@">
<NODE Name="W34Yo@D9cAR9">
<DATA Name="j8e39eIZWäeW5bA7" Type="BVSrkIqfsLP55HGD@65ZeGy5bofuNHagodcek">CcuWwIafXAqknJWcvKobp</DATA>
<DATA Name="W67FUahMcJ0L" Type="TdXnkIGbL7LtNHWczDmcs">k9@fEHGdV0YsB8qs2m0yQJGbyxV@uIagOgClk</DATA>
<DATA Name="hILK" Type="TdTrdGGbhTmnnJWc4äkUs">KyD6sJafZyzWBJWdDäGtbIOvtä78f0Gf15P1wU31qKC@TGaertGjh</DATA>
</NODE>
<NODE Name="WJcYäYLyxMy@BEMq6UYHWägqJ2TK">
<DATA Name="j8e39eIZWäeW5bA7" Type="BUTokIGbbngrNHqgnOHln">CoKVwIafJnbtAMqoZq1ad</DATA>
<DATA Name="W67FUahMcJ0L" Type="DZWHkIafvSLNNHWcGfoCh">ll0iEHGb3z0BQJGbzKV2uIWcHrwMl</DATA>
<DATA Name="hILK" Type="DZ7IdGGdInUKT@Wg2CCEnJWaPnAäd">OBEotJGb2BAdCJGbudFhUGqgw1REi</DATA>
</NODE>
<NODE Name="ZaäQDOQJ7O6FdThIjFRF8taGtEYc">
<DATA Name="j8e39eIZWäeW5bA7" Type="RdYDkIGbrIkGNHWc9vpye">lpLexIGbGNHEnJqge4Fxf</DATA>
<DATA Name="W67FUahMcJ0L" Type="DdcEkIafv71JNHWcV80yi">lpIfEHGb3DIyQJWbieiefXar58eMWKyAzOC@uIGcdDbPg</DATA>
<DATA Name="hILK" Type="Sc9odGGbgSDknJWc9Crln">KxU6sJWd0qV@TGafVyyWdTaPKanlyHWwZxQWBJaeX5BHs</DATA>
</NODE>
<NODE Name="LWm3äq88qfdYzvYc8d4PqxkäW67utEYc">
<DATA Name="j8e39eIZWäeW5bA7" Type="RZXDkIafrskGNHWcrLf3f">BovdxIGbWMrDnJqgYYnCl</DATA>
<DATA Name="W67FUahMcJ0L" Type="DZWnkIGbvSLtNHWcppSQp">okLjEHaf6yLCQJahSSqnR5WUCJF3uIWaUWKLf</DATA>
<DATA Name="hILK" Type="SYSsdGqfDIOv7ZajQGbp523ggCmonJag7gGNi">yBDptJGbNBzeCJqhkdzTSHajouuJa0GfTkGrP@q5PKxiUGGaR1Ovf</DATA>
</NODE>
<NODE Name="WTmXm2VcaKMc8d4PqxkäW67utEYc">
<DATA Name="j8e39eIZWäeW5bA7" Type="BYSskIGbbrfvNHqgemani">BätWwIafHVGuAMWk5bKdf</DATA>
<DATA Name="W67FUahMcJ0L" Type="Dd9DkIGbQ3LhpJWkIxrqn">EäXeEHGdSySZuIWcloYxQJqe@NtGk</DATA>
<DATA Name="hILK" Type="CcbFdGaf1RGAnJWcUCCBi">WBUotJafäBQdCJGbbrKhUGWc0uZCe</DATA>
</NODE>
</NODE>
<NODE Name="qqbBXBquwbz8">
<NODE Name="Rtcc">
<DATA Name="j8e39eIZWäeW5bA7" Type="RZXskIGbrskvNHWc8Vhnh">CduäwIafXBqznJqg0Lgyi</DATA>
<DATA Name="W67FUahMcJ0L" Type="DYbskIqhAäV6tWa42AxVfKarcv6NMZ39vR1xNHGaNm2Kh">läGeEHaf3nHxQJGbzyBZuIWcHNakl</DATA>
<DATA Name="hILK" Type="CäWEdGGb1OqAnJWcOzUZf">GCH5sJWdGn@0nSaBBY6e7RWmPWblQLqkVCDVBJGby34MBHGiU8MQd</DATA>
</NODE>
<NODE Name="sLmZ9gzH">
<DATA Name="j8e39eIZWäeW5bA7" Type="RccFkIahCAj7n5WUrHAHNHWaXC84n">BpGaxIqfL@4dBSycCuPtWIqqWNCAnJWa3By4f</DATA>
<DATA Name="W67FUahMcJ0L" Type="T9XHkIafL2MNNHqgxWL1m">FäWzEHafmoXSQJGbTyRivIWcvLAFh</DATA>
<DATA Name="hILK" Type="Sä7sdGGb@SMPtZaXgPConJWc1zqTl">MBIotJaf0BEdCJqhsFxhUGGbthssX4GLbBjTzHqc5pXPFYa3Xwh9j</DATA>
</NODE>
<NODE Name="VUXL0ajP9oXM9äeA2EYc">
<DATA Name="j8e39eIZWäeW5bA7" Type="RUbpkIWdUZyCL0ONBjtpmJyYXS5prM3urnArNHGaWkäJn">movdxIGbHMrDnJqgf3pEp</DATA>
<DATA Name="W67FUahMcJ0L" Type="TUbIkIWbruq3cTiXtf9El2W9LN1NNHagvOFus">lkLeEHGb9e4Y19aX3yLxQJGdmdAx0HqIzJFZuIqedsmaj</DATA>
<DATA Name="hILK" Type="DY8IdGGb2BDEnJWcdK68o">UCHltJaf8CDaCJGbM6IeUGWcZäK4q</DATA>
</NODE>
<NODE Name="sLmgtEWA">
<DATA Name="j8e39eIZWäeW5bA7" Type="RZWokIGbrsjrNHqgApoJo">msvVwIafHQrjnJWcR1fip</DATA>
<DATA Name="W67FUahMcJ0L" Type="TäXskIGbL3MyNHWc86Nho">l5@fEHGb3i0yQJGbztV@uIWcPG7lg</DATA>
<DATA Name="hILK" Type="SY7HdGafgCCDnJWcwMW@q">qX6XVLajQBEotJGbA00R3YGv4BAdCJGdq3HG8MWUIsuhUGWa49b@r</DATA>
</NODE>
<NODE Name="j6BIixjcNRqg20hu">
<DATA Name="j8e39eIZWäeW5bA7" Type="RVXEkIGbrokHNHqgFdnrd">läGWwIafGxDknJWcMHZJq</DATA>
<DATA Name="W67FUahMcJ0L" Type="TZ7EkIGbLSXKNHWcFNqze">Bk0uEHahi9jhwZ3hqYQpvNqp2oCz8WOfGTHi3@iiY8A7SX3oshFhQKamBy9Wm</DATA>
<DATA Name="hILK" Type="CccpdGGdscW6b4WE1RHknJWaQu2bs">UCE9sJGd415AKQ3g8CAZBJGbAuH2TGagvxjMn</DATA>
</NODE>
<NODE Name="T6PL34JYPWaFu6qg23Ju">
<DATA Name="j8e39eIZWäeW5bA7" Type="RZTnkIGbbpNYu8qdORFzoLi4FOnQu03oCJudKTOUrsgqNHqeEpRal">C9FaxIGbXwCAnJWczkWri</DATA>
<DATA Name="W67FUahMcJ0L" Type="TVTEkIWbmrzHyRGDlwqr0NyQLOIKNHGcCPbrg">o9@jEHaf6m0CQJafCxV3uIWcee1Vj</DATA>
<DATA Name="hILK" Type="494dhGGj1OCDnJWci6q1h">GxTotJGbVxPdCJqhMN1ZuYOFOqJ8YKWSy8bZQG3MX@UhUGagpAqEj</DATA>
</NODE>
</NODE>
<NODE Name="CnHPVDtF9WOA3yJu">
<NODE Name="BD1L6j4Ui08rz6pdOddGUcpYQNIPFGjUxGbcnl8Lwfgr">
<DATA Name="j8e39eIZWäeW5bA7" Type="Rä7DkIafrEvGNHWcsZA3l">BtLVwIafWRHjnJqg722io</DATA>
<DATA Name="W67FUahMcJ0L" Type="DU7DkIGbHkAKjVGTvNXJNHqgIIWYo">F5HjEHWb7@udwQajPzGp01yQmjICQJafTtC3uIGa8iHLh</DATA>
<DATA Name="hILK" Type="CUWndGGb1xqjnJqgicekg">Uoc0LManMhDVBJGbpsGZTGWcgcSIs</DATA>
</NODE>
<NODE Name="FX2Ye7dFP9FYPWt5naeGi9XH">
<DATA Name="j8e39eIZWäeW5bA7" Type="BVXDkIGbbokGNHWcSjVYj">PfOeDGaf0QqAxIWc@7mXi</DATA>
<DATA Name="W67FUahMcJ0L" Type="DVaokIWbXuquvKa4qG7NeNyQvO0tNHGcTjEGl">JevDlIGbNppHmJGb6GxU5GGbMokQUJqgj3UNn</DATA>
<DATA Name="hILK" Type="DV8ndGGb2yDjnJqgfRXcf">SiTptJaf6iPeCJGbKVTiUGqg4l3xf</DATA>
</NODE>
<NODE Name="8d6Jo6OF1lqgtEWA">
<DATA Name="j8e39eIZWäeW5bA7" Type="RäTnkIGbJ7mGoJWkrZdQg">movexIGbHMrEnJWcHsVFi</DATA>
<DATA Name="W67FUahMcJ0L" Type="DVaIkIWdYCrfA4ODkmV2cTOTkIqle3W9vO0NNHGaeH91g">BoMfEHWbmIpA6Wqkdo4tf3qqiDMyQJGbPNG@uIGct7Vll</DATA>
<DATA Name="hILK" Type="T9aJdGGbeRTiAPibhOGEnJWcäAE0n">ä3KvMMWjxlXdUGGb7YqOgZqcUCUäBJagSvvWd</DATA>
</NODE>
<NODE Name="1Au63wr76Rvi8DFB21BE">
<DATA Name="j8e39eIZWäeW5bA7" Type="RäSokIGbrEfrNHWcErijg">xMiäTKGjGRGznJWcovCYg</DATA>
<DATA Name="W67FUahMcJ0L" Type="D9XskIafv2MyNHWck5Nfh">kpIuEHqhneqQmZa68EcrX7qynrgiiIWU2DINQJGbyOCdvIaei0Rsl</DATA>
<DATA Name="hILK" Type="DäXndGGb2OrjnJWcVBLan">Po5uMMGjhpY92MWju0mIC1GvTVPs98qkmMydUGGcPiase</DATA>
</NODE>
<NODE Name="T6QPyOz76Rvi8DFB21BE">
<DATA Name="j8e39eIZWäeW5bA7" Type="BV7DkIGbbovGNHWcRj53d">läqZwIWbOEwag2iH4EOHWWyIGxnnnJGcUlJej</DATA>
<DATA Name="W67FUahMcJ0L" Type="TV8EkIGbLOYKNHqgCH66p">BlIjEHqhU2TSs6W17v0on4GLpt6YxHaQiAICQJGbPKC3uIGaBZPNs</DATA>
<DATA Name="hILK" Type="SY8HdGGdyG3ifHqYgCDDnJWawKrui">OBIktJGb2BEäBJafGExdUGqg6@Lsl</DATA>
</NODE>
<NODE Name="Bvb1NHyaZ0@RfmgaItG0qjJ@9My@dUNm29Z5o0@73tcr">
<DATA Name="j8e39eIZWäeW5bA7" Type="BccskIGbbHAuNHWcjuxUq">BätäwIafWxqznJqg9RUsf</DATA>
<DATA Name="W67FUahMcJ0L" Type="DZaIkIGbvS0NNHqgKh@wn">lp0iEHGb3D0BQJGbzOV2uIqgl2@ef</DATA>
<DATA Name="hILK" Type="TäbodGGbhPHjnJWcFtxQo">Z3cäLMapr4nCuYW1OCD@BJGbQLG3TGagQäoNn</DATA>
</NODE>
<NODE Name="pWHdUHQ02sädl9FTRILBpZZQPlzUjyxFUtdgJ4Fu">
<DATA Name="j8e39eIZWäeW5bA7" Type="BdcJkIGdzFvuvQycbIALNHWaSäDäm">B9u@wIqf5IcGDYGfJZz24JWMWwronJGcsITpj</DATA>
<DATA Name="W67FUahMcJ0L" Type="TdYrkIGbWnKENTiHL7MxNHqg2xfmn">x9Rt7IGj3n1CQJafzyW3uIWcRTDTo</DATA>
<DATA Name="hILK" Type="CcUodGGb1RnknJqgk@lbe">wBT9sJGdPlarhMqctLl@x83DN3O2TGafbCVTtLO7LBPZBJGcL7ySe</DATA>
</NODE>
</NODE>
</NODE></Root>
