<?xml version="1.0" encoding="utf-8"?><index><stem n="imagej"><phr n="ImageJ"><ent r="66" t="30" w="980" /><ent r="66" t="31" w="17" /><ent r="1000" t="32" w="1" /><ent r="62" t="32" w="3" /><ent r="3" t="32" w="5" /></phr></stem><stem n="java"><phr n="Java"><ent r="66" t="30" w="982" /><ent r="66" t="31" w="19" /><ent r="3" t="33" w="16" /><ent r="3" t="33" w="22" /><ent r="3" t="33" w="314" /><ent r="3" t="33" w="320" /><ent r="3" t="33" w="451" /><ent r="3" t="33" w="461" /><ent r="3" t="33" w="467" /><ent r="3" t="33" w="496" /><ent r="3" t="33" w="506" /><ent r="3" t="33" w="510" /><ent r="3" t="33" w="538" /><ent r="3" t="33" w="571" /><ent r="3" t="33" w="1492" /><ent r="3" t="33" w="1580" /><ent r="3" t="33" w="1593" /><ent r="3" t="33" w="1656" /><ent r="3" t="33" w="1665" /><ent r="3" t="33" w="1905" /><ent r="3" t="33" w="1914" /><ent r="3" t="33" w="1949" /><ent r="3" t="33" w="2003" /><ent r="3" t="33" w="2178" /><ent r="3" t="33" w="2689" /><ent r="3" t="33" w="2773" /><ent r="3" t="33" w="2777" /><ent r="3" t="33" w="2868" /><ent r="3" t="33" w="2900" /></phr><phr n="java"><ent r="3" t="33" w="521" /><ent r="3" t="33" w="2641" /><ent r="3" t="33" w="2788" /><ent r="3" t="33" w="2878" /><ent r="3" t="33" w="3039" /></phr><phr n="JAVA"><ent r="3" t="33" w="1123" /><ent r="3" t="33" w="1130" /><ent r="3" t="33" w="2350" /><ent r="3" t="33" w="2357" /><ent r="3" t="33" w="2605" /></phr></stem><stem n="jre"><phr n="JRE"><ent r="66" t="30" w="983" /><ent r="66" t="31" w="20" /><ent r="3" t="33" w="23" /></phr></stem><stem n="oracl"><phr n="Oracle"><ent r="66" t="30" w="984" /><ent r="66" t="31" w="21" /><ent r="1000" t="33" w="1" /><ent r="62" t="33" w="7" /><ent r="3" t="33" w="28" /><ent r="3" t="33" w="229" /><ent r="3" t="33" w="295" /><ent r="3" t="33" w="309" /><ent r="3" t="33" w="505" /><ent r="3" t="33" w="509" /><ent r="3" t="33" w="579" /><ent r="3" t="33" w="667" /><ent r="3" t="33" w="757" /><ent r="3" t="33" w="786" /><ent r="3" t="33" w="959" /><ent r="3" t="33" w="1047" /><ent r="3" t="33" w="1116" /><ent r="3" t="33" w="1118" /><ent r="3" t="33" w="1140" /><ent r="3" t="33" w="1154" /><ent r="3" t="33" w="1176" /><ent r="3" t="33" w="1180" /><ent r="3" t="33" w="1254" /><ent r="3" t="33" w="1341" /><ent r="3" t="33" w="1553" /><ent r="3" t="33" w="1600" /><ent r="3" t="33" w="1676" /><ent r="3" t="33" w="1786" /><ent r="3" t="33" w="1815" /><ent r="3" t="33" w="1925" /><ent r="3" t="33" w="2048" /><ent r="3" t="33" w="2075" /><ent r="3" t="33" w="2197" /><ent r="3" t="33" w="2270" /><ent r="3" t="33" w="2336" /><ent r="3" t="33" w="2373" /><ent r="3" t="33" w="2386" /><ent r="3" t="33" w="2435" /><ent r="3" t="33" w="2453" /><ent r="3" t="33" w="2496" /><ent r="3" t="33" w="2549" /><ent r="3" t="33" w="2587" /><ent r="3" t="33" w="2591" /><ent r="3" t="33" w="2651" /><ent r="3" t="33" w="2677" /><ent r="3" t="33" w="2679" /><ent r="3" t="33" w="2687" /><ent r="3" t="33" w="2755" /><ent r="3" t="33" w="2772" /><ent r="3" t="33" w="2776" /><ent r="3" t="33" w="2990" /><ent r="3" t="33" w="3001" /><ent r="3" t="33" w="3006" /><ent r="3" t="33" w="3024" /><ent r="3" t="33" w="3049" /><ent r="3" t="33" w="3053" /></phr><phr n="ORACLE"><ent r="3" t="33" w="34" /><ent r="3" t="33" w="37" /><ent r="3" t="33" w="827" /><ent r="3" t="33" w="859" /><ent r="3" t="33" w="899" /><ent r="3" t="33" w="909" /><ent r="3" t="33" w="1121" /><ent r="3" t="33" w="1127" /><ent r="3" t="33" w="2348" /><ent r="3" t="33" w="2354" /></phr><phr n="oracle"><ent r="3" t="33" w="518" /><ent r="3" t="33" w="1056" /><ent r="3" t="33" w="1161" /><ent r="3" t="33" w="2644" /><ent r="3" t="33" w="2785" /><ent r="3" t="33" w="2875" /><ent r="3" t="33" w="3036" /></phr></stem><stem n="binari"><phr n="Binary"><ent r="66" t="30" w="985" /><ent r="66" t="31" w="22" /><ent r="1000" t="33" w="2" /><ent r="62" t="33" w="8" /><ent r="3" t="33" w="29" /><ent r="3" t="33" w="1428" /><ent r="3" t="33" w="1450" /><ent r="3" t="33" w="1466" /><ent r="3" t="33" w="2919" /></phr><phr n="binary"><ent r="3" t="32" w="52" /><ent r="3" t="32" w="93" /><ent r="3" t="33" w="208" /><ent r="3" t="35" w="1463" /><ent r="3" t="42" w="230" /><ent r="3" t="42" w="274" /><ent r="3" t="42" w="809" /><ent r="3" t="42" w="850" /><ent r="3" t="42" w="1549" /><ent r="3" t="42" w="1589" /><ent r="3" t="42" w="1838" /><ent r="3" t="42" w="1878" /><ent r="3" t="43" w="45" /><ent r="3" t="43" w="53" /><ent r="3" t="43" w="209" /><ent r="3" t="43" w="246" /><ent r="3" t="44" w="18" /><ent r="3" t="44" w="54" /><ent r="3" t="46" w="19" /><ent r="3" t="46" w="56" /><ent r="3" t="47" w="25" /><ent r="3" t="47" w="64" /><ent r="3" t="48" w="32" /><ent r="3" t="48" w="68" /><ent r="3" t="51" w="264" /></phr><phr n="BINARY"><ent r="3" t="33" w="74" /></phr></stem><stem n="paint"><phr n="Paint"><ent r="66" t="30" w="990" /><ent r="66" t="31" w="27" /><ent r="1000" t="34" w="1" /><ent r="62" t="34" w="4" /><ent r="3" t="34" w="7" /><ent r="3" t="34" w="23" /><ent r="3" t="34" w="33" /></phr><phr n="paint"><ent r="3" t="34" w="78" /><ent r="3" t="34" w="169" /><ent r="3" t="34" w="230" /></phr></stem><stem n=".net"><phr n=".Net"><ent r="66" t="30" w="991" /><ent r="66" t="30" w="1014" /><ent r="66" t="31" w="28" /><ent r="66" t="31" w="51" /></phr><phr n=".NET"><ent r="1000" t="34" w="2" /><ent r="62" t="34" w="5" /><ent r="3" t="34" w="8" /><ent r="3" t="34" w="24" /><ent r="3" t="34" w="34" /><ent r="1000" t="38" w="2" /><ent r="62" t="38" w="6" /><ent r="3" t="38" w="403" /><ent r="3" t="38" w="423" /><ent r="3" t="38" w="506" /><ent r="3" t="38" w="539" /><ent r="3" t="38" w="580" /><ent r="3" t="38" w="673" /><ent r="3" t="38" w="747" /></phr><phr n=".net"><ent r="3" t="34" w="170" /><ent r="3" t="34" w="231" /></phr></stem><stem n="paint.net"><phr n="Paint.Net"><ent r="66" t="30" w="991" /><ent r="66" t="30" w="990" /><ent r="66" t="31" w="28" /><ent r="66" t="31" w="27" /></phr><phr n="Paint.NET"><ent r="1000" t="34" w="2" /><ent r="1000" t="34" w="1" /><ent r="62" t="34" w="5" /><ent r="62" t="34" w="4" /><ent r="3" t="34" w="8" /><ent r="3" t="34" w="7" /><ent r="3" t="34" w="24" /><ent r="3" t="34" w="23" /><ent r="3" t="34" w="34" /><ent r="3" t="34" w="33" /></phr><phr n="paint.net"><ent r="3" t="34" w="79" /><ent r="3" t="34" w="78" /><ent r="3" t="34" w="170" /><ent r="3" t="34" w="169" /><ent r="3" t="34" w="231" /><ent r="3" t="34" w="230" /></phr></stem><stem n="net"><phr n="Net"><ent r="66" t="30" w="991" /><ent r="66" t="30" w="1014" /><ent r="66" t="31" w="28" /><ent r="66" t="31" w="51" /></phr><phr n="NET"><ent r="1000" t="34" w="2" /><ent r="62" t="34" w="5" /><ent r="3" t="34" w="8" /><ent r="3" t="34" w="24" /><ent r="3" t="34" w="34" /><ent r="1000" t="38" w="2" /><ent r="62" t="38" w="6" /><ent r="3" t="38" w="403" /><ent r="3" t="38" w="410" /><ent r="3" t="38" w="423" /><ent r="3" t="38" w="506" /><ent r="3" t="38" w="539" /><ent r="3" t="38" w="580" /><ent r="3" t="38" w="673" /><ent r="3" t="38" w="747" /></phr><phr n="net"><ent r="3" t="34" w="79" /><ent r="3" t="34" w="89" /><ent r="3" t="34" w="170" /><ent r="3" t="34" w="231" /></phr></stem><stem n="notepad++"><phr n="Notepad++"><ent r="66" t="30" w="993" /><ent r="66" t="31" w="30" /></phr></stem><stem n="gnu"><phr n="GNU"><ent r="66" t="30" w="994" /><ent r="66" t="30" w="1004" /><ent r="66" t="30" w="1020" /><ent r="66" t="31" w="31" /><ent r="66" t="31" w="41" /><ent r="66" t="31" w="57" /><ent r="1000" t="35" w="1" /><ent r="62" t="35" w="6" /><ent r="3" t="35" w="79" /><ent r="3" t="35" w="142" /><ent r="3" t="35" w="2705" /><ent r="3" t="35" w="2766" /><ent r="3" t="35" w="2782" /><ent r="3" t="35" w="3058" /><ent r="3" t="36" w="24" /><ent r="3" t="36" w="34" /><ent r="3" t="36" w="38" /><ent r="3" t="36" w="50" /><ent r="3" t="36" w="88" /><ent r="3" t="36" w="112" /><ent r="3" t="36" w="174" /><ent r="3" t="36" w="191" /><ent r="3" t="42" w="1132" /></phr><phr n="gnu"><ent r="3" t="34" w="209" /><ent r="3" t="36" w="200" /></phr></stem><stem n="public"><phr n="Public"><ent r="66" t="30" w="996" /><ent r="66" t="30" w="1006" /><ent r="66" t="30" w="1022" /><ent r="66" t="31" w="33" /><ent r="66" t="31" w="43" /><ent r="66" t="31" w="59" /><ent r="3" t="35" w="81" /><ent r="3" t="35" w="109" /><ent r="3" t="35" w="145" /><ent r="3" t="35" w="172" /><ent r="3" t="35" w="542" /><ent r="3" t="35" w="2157" /><ent r="3" t="35" w="2707" /><ent r="3" t="35" w="2768" /><ent r="3" t="35" w="2784" /><ent r="3" t="35" w="2907" /><ent r="3" t="35" w="3016" /><ent r="3" t="35" w="3061" /><ent r="3" t="36" w="115" /><ent r="3" t="36" w="178" /><ent r="3" t="36" w="194" /><ent r="3" t="42" w="1133" /><ent r="3" t="51" w="107" /><ent r="3" t="51" w="509" /><ent r="3" t="51" w="2372" /><ent r="3" t="51" w="2399" /></phr><phr n="Publication"><ent r="3" t="33" w="2180" /><ent r="3" t="33" w="2232" /><ent r="3" t="33" w="2257" /><ent r="3" t="33" w="2310" /><ent r="3" t="33" w="2543" /><ent r="3" t="33" w="2556" /><ent r="3" t="33" w="2567" /><ent r="3" t="33" w="2574" /></phr><phr n="PUBLIC"><ent r="1000" t="35" w="3" /><ent r="62" t="35" w="8" /><ent r="3" t="51" w="526" /></phr><phr n="public"><ent r="3" t="35" w="1989" /><ent r="3" t="35" w="2588" /><ent r="3" t="38" w="614" /><ent r="3" t="38" w="626" /><ent r="3" t="41" w="141" /></phr><phr n="publically"><ent r="3" t="42" w="1102" /></phr></stem><stem n="7zip"><phr n="7Zip"><ent r="66" t="30" w="999" /><ent r="66" t="31" w="36" /><ent r="1000" t="36" w="1" /><ent r="62" t="36" w="3" /></phr></stem><stem n="usb"><phr n="USB"><ent r="66" t="30" w="1001" /><ent r="66" t="31" w="38" /></phr></stem><stem n="usb-disk"><phr n="USB-Disk"><ent r="66" t="30" w="1001" /><ent r="66" t="31" w="38" /></phr></stem><stem n="usb-disk-ejector"><phr n="USB-Disk-Ejector"><ent r="66" t="30" w="1001" /><ent r="66" t="31" w="38" /></phr></stem><stem n="disk"><phr n="Disk"><ent r="66" t="30" w="1002" /><ent r="66" t="31" w="39" /></phr></stem><stem n="disk-ejector"><phr n="Disk-Ejector"><ent r="66" t="30" w="1002" /><ent r="66" t="31" w="39" /></phr></stem><stem n="ejector"><phr n="Ejector"><ent r="66" t="30" w="1003" /><ent r="66" t="31" w="40" /></phr></stem><stem n="-disk-ejector:"><phr n="-Disk-Ejector:"><ent r="66" t="30" w="1004" /><ent r="66" t="30" w="1005" /><ent r="66" t="31" w="41" /><ent r="66" t="31" w="42" /></phr></stem><stem n="microsoft"><phr n="Microsoft"><ent r="66" t="30" w="1009" /><ent r="66" t="30" w="1013" /><ent r="66" t="31" w="46" /><ent r="66" t="31" w="50" /><ent r="1000" t="37" w="1" /><ent r="62" t="37" w="5" /><ent r="3" t="37" w="37" /><ent r="3" t="37" w="388" /><ent r="1000" t="38" w="1" /><ent r="62" t="38" w="5" /><ent r="3" t="38" w="24" /><ent r="3" t="38" w="26" /><ent r="3" t="38" w="55" /><ent r="3" t="38" w="224" /><ent r="3" t="38" w="237" /><ent r="3" t="38" w="533" /><ent r="3" t="38" w="564" /><ent r="3" t="38" w="585" /><ent r="3" t="38" w="718" /><ent r="3" t="38" w="726" /><ent r="3" t="38" w="758" /><ent r="3" t="38" w="779" /><ent r="3" t="38" w="932" /><ent r="3" t="38" w="1046" /><ent r="3" t="38" w="1154" /><ent r="3" t="38" w="1276" /><ent r="3" t="38" w="1961" /><ent r="3" t="38" w="1972" /><ent r="3" t="38" w="1979" /><ent r="3" t="38" w="1984" /><ent r="3" t="39" w="27" /><ent r="3" t="39" w="68" /><ent r="3" t="39" w="158" /><ent r="3" t="39" w="164" /><ent r="3" t="39" w="492" /><ent r="3" t="39" w="529" /><ent r="3" t="39" w="550" /><ent r="3" t="39" w="661" /><ent r="3" t="39" w="730" /><ent r="3" t="39" w="1270" /><ent r="3" t="39" w="1378" /><ent r="3" t="39" w="1451" /><ent r="3" t="39" w="1568" /></phr><phr n="microsoft"><ent r="3" t="37" w="54" /><ent r="3" t="37" w="473" /><ent r="3" t="39" w="251" /><ent r="3" t="39" w="907" /></phr><phr n="MICROSOFT"><ent r="3" t="38" w="142" /><ent r="3" t="38" w="791" /><ent r="3" t="38" w="870" /><ent r="3" t="38" w="878" /><ent r="3" t="38" w="902" /><ent r="3" t="38" w="1201" /><ent r="3" t="38" w="1297" /><ent r="3" t="38" w="1337" /><ent r="3" t="38" w="1409" /><ent r="3" t="38" w="1420" /><ent r="3" t="38" w="1447" /><ent r="3" t="38" w="1483" /><ent r="3" t="38" w="1610" /><ent r="3" t="38" w="1741" /><ent r="3" t="38" w="1793" /><ent r="1000" t="39" w="1" /><ent r="62" t="39" w="8" /><ent r="3" t="39" w="15" /><ent r="3" t="39" w="1126" /><ent r="3" t="39" w="1157" /><ent r="3" t="39" w="1186" /><ent r="3" t="42" w="5" /></phr></stem><stem n="sysintern"><phr n="Sysinternals"><ent r="66" t="30" w="1010" /><ent r="66" t="31" w="47" /><ent r="1000" t="37" w="2" /><ent r="62" t="37" w="6" /><ent r="3" t="37" w="31" /><ent r="3" t="37" w="74" /><ent r="3" t="37" w="178" /><ent r="3" t="37" w="339" /><ent r="3" t="37" w="689" /><ent r="3" t="37" w="833" /><ent r="3" t="37" w="941" /><ent r="3" t="37" w="1014" /><ent r="3" t="37" w="1131" /></phr><phr n="sysinternals"><ent r="3" t="37" w="56" /><ent r="3" t="37" w="720" /><ent r="3" t="37" w="749" /></phr></stem><stem n="pstool"><phr n="PSTools"><ent r="66" t="30" w="1011" /><ent r="66" t="31" w="48" /><ent r="1000" t="37" w="3" /><ent r="62" t="37" w="7" /></phr></stem><stem n="framework"><phr n="Framework"><ent r="66" t="30" w="1015" /><ent r="66" t="31" w="52" /><ent r="1000" t="38" w="3" /><ent r="62" t="38" w="7" /><ent r="3" t="38" w="404" /></phr></stem><stem n="directx"><phr n="DirectX"><ent r="66" t="30" w="1017" /><ent r="66" t="31" w="54" /></phr><phr n="DIRECTX"><ent r="1000" t="39" w="2" /><ent r="62" t="39" w="9" /><ent r="3" t="39" w="304" /><ent r="3" t="39" w="321" /></phr></stem><stem n="imdisk"><phr n="imdisk"><ent r="66" t="30" w="1019" /><ent r="66" t="31" w="56" /></phr></stem><stem n="boost"><phr n="Boost"><ent r="66" t="30" w="1025" /><ent r="66" t="31" w="62" /><ent r="1000" t="40" w="1" /><ent r="62" t="40" w="4" /><ent r="3" t="40" w="7" /></phr></stem><stem n="openssl"><phr n="OpenSSL"><ent r="66" t="30" w="1028" /><ent r="66" t="31" w="65" /><ent r="1000" t="41" w="1" /><ent r="62" t="41" w="3" /><ent r="3" t="41" w="5" /><ent r="3" t="41" w="75" /><ent r="3" t="41" w="101" /><ent r="3" t="42" w="15" /><ent r="3" t="42" w="24" /><ent r="3" t="42" w="109" /><ent r="3" t="42" w="124" /><ent r="3" t="42" w="161" /><ent r="3" t="42" w="207" /><ent r="3" t="42" w="217" /><ent r="3" t="42" w="331" /><ent r="3" t="42" w="338" /><ent r="3" t="42" w="349" /><ent r="3" t="42" w="352" /><ent r="3" t="42" w="395" /><ent r="3" t="42" w="399" /><ent r="3" t="42" w="411" /><ent r="3" t="42" w="435" /><ent r="3" t="42" w="442" /><ent r="3" t="42" w="456" /><ent r="3" t="42" w="492" /></phr><phr n="openssl"><ent r="3" t="42" w="165" /><ent r="3" t="42" w="167" /><ent r="3" t="42" w="342" /><ent r="3" t="42" w="379" /><ent r="3" t="42" w="381" /><ent r="3" t="42" w="446" /></phr></stem><stem n="boringssl"><phr n="BoringSSL"><ent r="66" t="30" w="1030" /><ent r="66" t="31" w="67" /><ent r="1000" t="42" w="1" /><ent r="62" t="42" w="3" /><ent r="3" t="42" w="10" /><ent r="3" t="42" w="54" /><ent r="3" t="42" w="1145" /><ent r="3" t="42" w="1511" /><ent r="3" t="42" w="1526" /><ent r="3" t="42" w="1779" /><ent r="3" t="42" w="1816" /></phr></stem><stem n="rapidjson"><phr n="RapidJSON"><ent r="66" t="30" w="1032" /><ent r="66" t="31" w="69" /><ent r="1000" t="43" w="1" /><ent r="62" t="43" w="3" /><ent r="3" t="43" w="16" /><ent r="3" t="43" w="44" /><ent r="3" t="43" w="52" /><ent r="3" t="43" w="69" /><ent r="3" t="43" w="77" /><ent r="3" t="43" w="104" /><ent r="3" t="43" w="130" /></phr></stem><stem n="protobuf"><phr n="protobuf"><ent r="66" t="30" w="1034" /><ent r="66" t="31" w="71" /><ent r="1000" t="44" w="1" /><ent r="62" t="44" w="3" /></phr></stem><stem n="grpc"><phr n="grpc"><ent r="66" t="30" w="1036" /><ent r="66" t="31" w="73" /><ent r="3" t="45" w="17" /><ent r="3" t="45" w="18" /></phr></stem><stem n="apach"><phr n="Apache"><ent r="66" t="30" w="1037" /><ent r="66" t="31" w="74" /><ent r="3" t="41" w="57" /><ent r="1000" t="45" w="1" /><ent r="62" t="45" w="9" /><ent r="3" t="45" w="23" /><ent r="3" t="45" w="1484" /><ent r="3" t="45" w="1493" /><ent r="3" t="45" w="1576" /></phr><phr n="apache"><ent r="3" t="45" w="31" /><ent r="3" t="45" w="1606" /></phr></stem><stem n="httpp"><phr n="httpp"><ent r="66" t="30" w="1040" /><ent r="66" t="31" w="77" /><ent r="1000" t="46" w="1" /><ent r="62" t="46" w="3" /></phr></stem><stem n="thirdparti"><phr n="thirdparty"><ent r="66" t="30" w="1042" /><ent r="66" t="30" w="1046" /><ent r="66" t="30" w="1049" /><ent r="66" t="31" w="79" /><ent r="66" t="31" w="83" /><ent r="66" t="31" w="86" /></phr></stem><stem n="/ez-http"><phr n="/ez-http"><ent r="66" t="30" w="1043" /><ent r="66" t="31" w="80" /></phr></stem><stem n="ez"><phr n="ez"><ent r="66" t="30" w="1043" /><ent r="66" t="31" w="80" /><ent r="1000" t="47" w="1" /><ent r="63" t="47" w="4" /><ent r="3" t="47" w="97" /></phr></stem><stem n="ez-http"><phr n="ez-http"><ent r="66" t="30" w="1043" /><ent r="66" t="31" w="80" /><ent r="1000" t="47" w="1" /><ent r="63" t="47" w="4" /><ent r="3" t="47" w="97" /></phr></stem><stem n="http"><phr n="http"><ent r="66" t="30" w="1044" /><ent r="66" t="30" w="1050" /><ent r="66" t="31" w="81" /><ent r="66" t="31" w="87" /><ent r="3" t="33" w="516" /><ent r="3" t="33" w="1054" /><ent r="3" t="33" w="1159" /><ent r="3" t="33" w="2783" /><ent r="3" t="33" w="2873" /><ent r="3" t="33" w="3034" /><ent r="3" t="34" w="86" /><ent r="3" t="34" w="184" /><ent r="3" t="34" w="194" /><ent r="3" t="34" w="207" /><ent r="3" t="36" w="198" /><ent r="3" t="42" w="340" /><ent r="3" t="42" w="444" /><ent r="3" t="45" w="29" /><ent r="3" t="45" w="1604" /><ent r="1000" t="47" w="2" /><ent r="63" t="47" w="5" /><ent r="3" t="47" w="98" /><ent r="1000" t="49" w="1" /><ent r="62" t="49" w="4" /></phr><phr n="https"><ent r="3" t="42" w="65" /><ent r="3" t="42" w="1298" /></phr></stem><stem n="/bin2ascii"><phr n="/bin2ascii"><ent r="66" t="30" w="1047" /><ent r="66" t="31" w="84" /></phr></stem><stem n="thirdparty/bin2ascii"><phr n="thirdparty/bin2ascii"><ent r="66" t="30" w="1047" /><ent r="66" t="30" w="1046" /><ent r="66" t="31" w="84" /><ent r="66" t="31" w="83" /></phr></stem><stem n="bin2ascii"><phr n="bin2ascii"><ent r="66" t="30" w="1047" /><ent r="66" t="31" w="84" /><ent r="1000" t="48" w="1" /><ent r="62" t="48" w="3" /></phr></stem><stem n="thirdparty/http"><phr n="thirdparty/http"><ent r="66" t="30" w="1050" /><ent r="66" t="30" w="1049" /><ent r="66" t="31" w="87" /><ent r="66" t="31" w="86" /></phr></stem><stem n="/http_parser"><phr n="/http_parser"><ent r="66" t="30" w="1051" /><ent r="66" t="31" w="88" /></phr></stem><stem n="thirdparty/http_pars"><phr n="thirdparty/http_parser"><ent r="66" t="30" w="1051" /><ent r="66" t="30" w="1049" /><ent r="66" t="31" w="88" /><ent r="66" t="31" w="86" /></phr></stem><stem n="parser"><phr n="parser"><ent r="66" t="30" w="1051" /><ent r="66" t="31" w="88" /><ent r="1000" t="49" w="2" /><ent r="62" t="49" w="5" /></phr></stem><stem n="tcl"><phr n="TCL"><ent r="66" t="30" w="1053" /><ent r="66" t="31" w="90" /><ent r="1000" t="50" w="1" /><ent r="62" t="50" w="4" /></phr></stem><stem n="nullsoft"><phr n="Nullsoft"><ent r="65" t="30" w="1056" /><ent r="65" t="31" w="93" /><ent r="1000" t="51" w="1" /><ent r="62" t="51" w="7" /></phr></stem><stem n="scriptabl"><phr n="Scriptable"><ent r="65" t="30" w="1057" /><ent r="65" t="31" w="94" /><ent r="1000" t="51" w="2" /><ent r="62" t="51" w="8" /></phr></stem><stem n="nsi"><phr n="NSIS"><ent r="65" t="30" w="1060" /><ent r="65" t="31" w="97" /><ent r="1000" t="51" w="5" /><ent r="62" t="51" w="11" /><ent r="3" t="51" w="39" /><ent r="3" t="51" w="74" /><ent r="3" t="51" w="88" /><ent r="3" t="51" w="101" /><ent r="3" t="51" w="2336" /><ent r="3" t="51" w="2360" /><ent r="3" t="51" w="2389" /></phr></stem><stem n="(nsis)"><phr n="(NSIS)"><ent r="65" t="30" w="1061" /><ent r="65" t="31" w="98" /><ent r="1000" t="51" w="6" /><ent r="62" t="51" w="12" /></phr></stem><stem n="&amp;"><phr n="&amp;"><ent r="4" t="30" w="1063" /></phr></stem><stem n="question"><phr n="questions"><ent r="3" t="30" w="1071" /><ent r="3" t="38" w="1947" /></phr></stem><stem n="concern"><phr n="concerning"><ent r="3" t="30" w="1072" /></phr><phr n="concerns"><ent r="3" t="35" w="2185" /></phr><phr n="concerne"><ent r="3" t="37" w="1060" /><ent r="3" t="38" w="1283" /><ent r="3" t="39" w="1497" /></phr><phr n="CONCERNE"><ent r="3" t="38" w="1818" /></phr><phr n="concernant"><ent r="3" t="38" w="1948" /></phr></stem><stem n="reason"><phr n="reason"><ent r="3" t="30" w="1085" /><ent r="3" t="35" w="1787" /><ent r="3" t="45" w="1462" /></phr><phr n="reasonably"><ent r="3" t="35" w="1031" /><ent r="3" t="51" w="1286" /><ent r="3" t="51" w="2039" /></phr><phr n="reasonable"><ent r="3" t="38" w="1095" /><ent r="3" t="45" w="1151" /><ent r="3" t="51" w="1204" /><ent r="3" t="51" w="2007" /></phr><phr n="REASON"><ent r="3" t="38" w="1182" /></phr></stem><stem n="(+49)"><phr n="(+49)"><ent r="3" t="30" w="1102" /></phr></stem><stem n="08121"><phr n="08121"><ent r="3" t="30" w="1102" /></phr></stem><stem n="8020"><phr n="8020"><ent r="3" t="30" w="1103" /></phr></stem><stem n="email"><phr n="email"><ent r="3" t="30" w="1105" /><ent r="3" t="33" w="356" /></phr></stem><stem n="multidimension"><phr n="multidimensional"><ent r="3" t="32" w="8" /></phr></stem><stem n="analysi"><phr n="analysis"><ent r="3" t="32" w="12" /></phr></stem><stem n="2009"><phr n="2009"><ent r="3" t="32" w="16" /><ent r="3" t="42" w="1535" /></phr></stem><stem n="2013"><phr n="2013"><ent r="3" t="32" w="17" /><ent r="3" t="43" w="195" /><ent r="3" t="48" w="21" /></phr></stem><stem n="board"><phr n="Board"><ent r="3" t="32" w="18" /></phr></stem><stem n="regent"><phr n="Regents"><ent r="3" t="32" w="20" /></phr><phr n="REGENTS"><ent r="3" t="43" w="310" /><ent r="3" t="43" w="344" /></phr></stem><stem n="univers"><phr n="University"><ent r="3" t="32" w="23" /></phr></stem><stem n="wisconsin"><phr n="Wisconsin"><ent r="3" t="32" w="26" /></phr></stem><stem n="wisconsin-madison"><phr n="Wisconsin-Madison"><ent r="3" t="32" w="26" /></phr></stem><stem n="madison"><phr n="Madison"><ent r="3" t="32" w="27" /></phr></stem><stem n="-madison,"><phr n="-Madison,"><ent r="3" t="32" w="28" /><ent r="3" t="32" w="28" /></phr></stem><stem n="broad"><phr n="Broad"><ent r="3" t="32" w="28" /></phr></stem><stem n="institut"><phr n="Institute"><ent r="3" t="32" w="29" /><ent r="3" t="32" w="38" /></phr><phr n="institute"><ent r="3" t="45" w="673" /></phr><phr n="institutes"><ent r="3" t="51" w="1866" /><ent r="3" t="51" w="1917" /></phr></stem><stem n="mit"><phr n="MIT"><ent r="3" t="32" w="31" /><ent r="3" t="42" w="84" /><ent r="3" t="42" w="1285" /><ent r="3" t="43" w="58" /><ent r="3" t="43" w="84" /><ent r="3" t="43" w="114" /><ent r="3" t="43" w="165" /><ent r="3" t="43" w="642" /></phr><phr n="mit"><ent r="3" t="42" w="1301" /></phr></stem><stem n="harvard"><phr n="Harvard"><ent r="3" t="32" w="33" /></phr></stem><stem n="max"><phr n="Max"><ent r="3" t="32" w="35" /></phr></stem><stem n="planck"><phr n="Planck"><ent r="3" t="32" w="36" /></phr></stem><stem n="molecular"><phr n="Molecular"><ent r="3" t="32" w="40" /></phr></stem><stem n="cell"><phr n="Cell"><ent r="3" t="32" w="41" /></phr><phr n="celles"><ent r="3" t="37" w="1225" /><ent r="3" t="39" w="1662" /></phr></stem><stem n="biologi"><phr n="Biology"><ent r="3" t="32" w="42" /></phr></stem><stem n="genet"><phr n="Genetics"><ent r="3" t="32" w="44" /></phr></stem><stem n="redistribut"><phr n="Redistribution"><ent r="3" t="32" w="46" /><ent r="3" t="33" w="1671" /><ent r="3" t="33" w="1920" /><ent r="3" t="42" w="224" /><ent r="3" t="42" w="803" /><ent r="3" t="42" w="1543" /><ent r="3" t="42" w="1832" /><ent r="3" t="43" w="203" /><ent r="3" t="44" w="12" /><ent r="3" t="45" w="730" /><ent r="3" t="46" w="13" /><ent r="3" t="47" w="19" /><ent r="3" t="48" w="26" /><ent r="3" t="51" w="258" /></phr><phr n="Redistributions"><ent r="3" t="32" w="70" /><ent r="3" t="32" w="91" /><ent r="3" t="42" w="250" /><ent r="3" t="42" w="272" /><ent r="3" t="42" w="416" /><ent r="3" t="42" w="828" /><ent r="3" t="42" w="848" /><ent r="3" t="42" w="1567" /><ent r="3" t="42" w="1587" /><ent r="3" t="42" w="1856" /><ent r="3" t="42" w="1876" /><ent r="3" t="43" w="225" /><ent r="3" t="43" w="244" /><ent r="3" t="44" w="34" /><ent r="3" t="44" w="52" /><ent r="3" t="46" w="35" /><ent r="3" t="46" w="54" /><ent r="3" t="47" w="42" /><ent r="3" t="47" w="62" /><ent r="3" t="48" w="48" /><ent r="3" t="48" w="66" /><ent r="3" t="51" w="281" /></phr><phr n="REDISTRIBUTABLES"><ent r="3" t="33" w="1887" /></phr><phr n="redistributable"><ent r="3" t="33" w="1946" /></phr><phr n="Redistributables"><ent r="3" t="33" w="1952" /><ent r="3" t="33" w="1959" /><ent r="3" t="33" w="1980" /><ent r="3" t="33" w="1996" /><ent r="3" t="33" w="2023" /><ent r="3" t="33" w="2029" /></phr><phr n="REDISTRIBUTION"><ent r="3" t="33" w="2661" /></phr><phr n="redistribute"><ent r="3" t="33" w="2665" /><ent r="3" t="35" w="959" /><ent r="3" t="35" w="1706" /><ent r="3" t="35" w="2604" /><ent r="3" t="35" w="2693" /><ent r="3" t="35" w="2879" /><ent r="3" t="36" w="100" /><ent r="3" t="50" w="82" /><ent r="4" t="50" w="187" /><ent r="3" t="51" w="169" /></phr><phr n="redistributed"><ent r="3" t="33" w="2838" /></phr><phr n="redistribution"><ent r="3" t="35" w="1865" /></phr><phr n="REDISTRIBUTE"><ent r="3" t="35" w="2472" /></phr><phr n="redistributing"><ent r="3" t="45" w="1240" /><ent r="3" t="45" w="1379" /></phr></stem><stem n="met"><phr n="met"><ent r="3" t="32" w="67" /><ent r="3" t="42" w="246" /><ent r="3" t="42" w="825" /><ent r="3" t="42" w="1565" /><ent r="3" t="42" w="1854" /><ent r="3" t="43" w="223" /><ent r="3" t="44" w="32" /><ent r="3" t="46" w="33" /><ent r="3" t="47" w="39" /><ent r="3" t="48" w="46" /><ent r="3" t="51" w="278" /></phr></stem><stem n="retain"><phr n="retain"><ent r="3" t="32" w="75" /><ent r="3" t="42" w="255" /><ent r="3" t="42" w="422" /><ent r="3" t="42" w="833" /><ent r="3" t="42" w="1572" /><ent r="3" t="42" w="1861" /><ent r="3" t="43" w="230" /><ent r="3" t="44" w="39" /><ent r="3" t="45" w="807" /><ent r="3" t="46" w="40" /><ent r="3" t="47" w="47" /><ent r="3" t="48" w="53" /><ent r="3" t="51" w="286" /></phr><phr n="retained"><ent r="3" t="33" w="665" /></phr><phr n="retains"><ent r="3" t="38" w="759" /></phr></stem><stem n="notic"><phr n="notice"><ent r="3" t="32" w="79" /><ent r="3" t="32" w="100" /><ent r="3" t="33" w="957" /><ent r="3" t="33" w="1801" /><ent r="3" t="33" w="2062" /><ent r="3" t="33" w="2553" /><ent r="3" t="33" w="2558" /><ent r="3" t="33" w="2582" /><ent r="3" t="33" w="2720" /><ent r="3" t="33" w="2723" /><ent r="3" t="33" w="2737" /><ent r="3" t="34" w="238" /><ent r="3" t="34" w="242" /><ent r="3" t="35" w="525" /><ent r="3" t="35" w="714" /><ent r="3" t="35" w="938" /><ent r="3" t="35" w="941" /><ent r="3" t="35" w="2659" /><ent r="3" t="35" w="2836" /><ent r="3" t="39" w="481" /><ent r="3" t="39" w="522" /><ent r="3" t="42" w="260" /><ent r="3" t="42" w="282" /><ent r="3" t="42" w="837" /><ent r="3" t="42" w="858" /><ent r="3" t="42" w="1181" /><ent r="3" t="42" w="1185" /><ent r="3" t="42" w="1385" /><ent r="3" t="42" w="1389" /><ent r="3" t="42" w="1577" /><ent r="3" t="42" w="1597" /><ent r="3" t="42" w="1866" /><ent r="3" t="42" w="1886" /><ent r="3" t="43" w="234" /><ent r="3" t="43" w="253" /><ent r="3" t="43" w="534" /><ent r="3" t="43" w="538" /><ent r="3" t="43" w="717" /><ent r="3" t="43" w="721" /><ent r="3" t="44" w="43" /><ent r="3" t="44" w="61" /><ent r="3" t="45" w="262" /><ent r="3" t="45" w="1502" /><ent r="3" t="45" w="1557" /><ent r="3" t="46" w="44" /><ent r="3" t="46" w="63" /><ent r="3" t="47" w="51" /><ent r="3" t="47" w="71" /><ent r="3" t="48" w="57" /><ent r="3" t="48" w="75" /><ent r="3" t="49" w="86" /><ent r="3" t="49" w="90" /><ent r="3" t="50" w="163" /><ent r="3" t="50" w="167" /><ent r="3" t="51" w="243" /><ent r="3" t="51" w="290" /></phr><phr n="notices"><ent r="3" t="33" w="1757" /><ent r="3" t="33" w="2017" /><ent r="3" t="33" w="2305" /><ent r="3" t="33" w="2853" /><ent r="3" t="35" w="723" /><ent r="3" t="35" w="841" /><ent r="3" t="35" w="2617" /><ent r="3" t="40" w="83" /><ent r="3" t="42" w="740" /><ent r="3" t="45" w="795" /><ent r="3" t="45" w="825" /><ent r="3" t="45" w="835" /><ent r="3" t="45" w="878" /><ent r="3" t="45" w="886" /><ent r="3" t="45" w="946" /><ent r="3" t="45" w="972" /><ent r="3" t="45" w="996" /><ent r="3" t="51" w="1263" /></phr><phr n="NOTICE"><ent r="3" t="33" w="2697" /><ent r="3" t="45" w="855" /><ent r="3" t="45" w="882" /><ent r="3" t="45" w="908" /><ent r="3" t="45" w="953" /><ent r="3" t="45" w="986" /><ent r="3" t="45" w="1168" /></phr></stem></index>